jupyter_exam/__init__.py
jupyter_exam/_version.py
jupyter_exam/handlers.py
jupyter_exam/labextension/package.json
jupyter_exam/labextension/schemas/jupyter_exam/package.json.orig
jupyter_exam/labextension/schemas/jupyter_exam/plugin.json
jupyter_exam/labextension/static/675.eaf512d9ffd2ac949f32.js
jupyter_exam/labextension/static/728.1ebf16f75552ad812499.js
jupyter_exam/labextension/static/remoteEntry.d8c1eb7d323acee40157.js
jupyter_exam/labextension/static/style.js
jupyter_exam/labextension/static/third-party-licenses.json
jupyter_exam-0.5.0.data/data/etc/jupyter/jupyter_server_config.d/jupyter_exam.json
jupyter_exam-0.5.0.data/data/share/jupyter/labextensions/jupyter_exam/package.json
jupyter_exam-0.5.0.data/data/share/jupyter/labextensions/jupyter_exam/schemas/jupyter_exam/package.json.orig
jupyter_exam-0.5.0.data/data/share/jupyter/labextensions/jupyter_exam/schemas/jupyter_exam/plugin.json
jupyter_exam-0.5.0.data/data/share/jupyter/labextensions/jupyter_exam/static/675.eaf512d9ffd2ac949f32.js
jupyter_exam-0.5.0.data/data/share/jupyter/labextensions/jupyter_exam/static/728.1ebf16f75552ad812499.js
jupyter_exam-0.5.0.data/data/share/jupyter/labextensions/jupyter_exam/static/remoteEntry.d8c1eb7d323acee40157.js
jupyter_exam-0.5.0.data/data/share/jupyter/labextensions/jupyter_exam/static/style.js
jupyter_exam-0.5.0.data/data/share/jupyter/labextensions/jupyter_exam/static/third-party-licenses.json
jupyter_exam-0.5.0.data/data/share/jupyter/labextensions/jupyter_exam/install.json
jupyter_exam-0.5.0.dist-info/METADATA
jupyter_exam-0.5.0.dist-info/WHEEL
jupyter_exam-0.5.0.dist-info/licenses/LICENSE
jupyter_exam-0.5.0.dist-info/RECORD
