Metadata-Version: 2.4
Name: jupyter_exam
Version: 0.5.0
Summary: A JupyterLab extension to collect exam files
Project-URL: Homepage, https://github.com/mhuttner/jupyter_exam
Project-URL: Bug Tracker, https://github.com/mhuttner/jupyter_exam/issues
Project-URL: Repository, https://github.com/mhuttner/jupyter_exam.git
Author-email: Michael Huttner <michael@mhuttner.com>
License: MIT License
License-File: LICENSE
Keywords: jupyter,jupyterlab,jupyterlab-extension
Classifier: Framework :: Jupyter
Classifier: Framework :: Jupyter :: JupyterLab
Classifier: Framework :: Jupyter :: JupyterLab :: 4
Classifier: Framework :: Jupyter :: JupyterLab :: Extensions
Classifier: Framework :: Jupyter :: JupyterLab :: Extensions :: Prebuilt
Classifier: License :: OSI Approved :: BSD License
Classifier: Programming Language :: Python
Classifier: Programming Language :: Python :: 3
Classifier: Programming Language :: Python :: 3.9
Classifier: Programming Language :: Python :: 3.10
Classifier: Programming Language :: Python :: 3.11
Classifier: Programming Language :: Python :: 3.12
Classifier: Programming Language :: Python :: 3.13
Requires-Python: >=3.8
Requires-Dist: jupyter-server<3,>=2.4.0
